corigami/__init__.py
corigami/data/__init__.py
corigami/data/chromosome_dataset.py
corigami/data/data_feature.py
corigami/data/genome_dataset.py
corigami/inference/__init__.py
corigami/inference/editing.py
corigami/inference/prediction.py
corigami/inference/screening.py
corigami/inference/utils/__init__.py
corigami/inference/utils/inference_utils.py
corigami/inference/utils/model_utils.py
corigami/inference/utils/plot_utils.py
corigami/model/__init__.py
corigami/model/blocks.py
corigami/model/corigami_models.py
corigami/training/main.py
corigami_demo-0.0.1.dist-info/METADATA
corigami_demo-0.0.1.dist-info/WHEEL
corigami_demo-0.0.1.dist-info/entry_points.txt
corigami_demo-0.0.1.dist-info/top_level.txt
corigami_demo-0.0.1.dist-info/RECORD
