Metadata-Version: 2.1
Name: corigami-demo
Version: 0.0.1
Summary: C.Origami: cell type-specific chromatin structure prediction.
Author-email: Jimin Tan <tanjimin@nyu.edu>, Nina Shenker-Tauris <shenkn01@nyu.edu>
Maintainer-email: Jimin Tan <tanjimin@nyu.edu>, Nina Shenker-Tauris <shenkn01@nyu.edu>
Project-URL: Homepage, https://github.com/tanjimin/C.Origami
Project-URL: Repository, https://github.com/tanjimin/C.Origami
Keywords: deep learning,chromatin,prediction,cell type-specific,epigenetics
Classifier: Programming Language :: Python
Classifier: Programming Language :: Python :: 3
Requires-Python: >=3.9
Requires-Dist: torch (>=1.12.0)
Requires-Dist: pandas (>=1.3.0)
Requires-Dist: matplotlib (>=3.3.2)
Requires-Dist: omegaconf (>=2.1.1)
Requires-Dist: tqdm (>=4.64.0)
Requires-Dist: pybigwig (==0.3.18)
Provides-Extra: training
Requires-Dist: pytorch-lightning (==1.5.8) ; extra == 'training'
Requires-Dist: lightning-bolts (==0.5.0) ; extra == 'training'
Requires-Dist: scikit-image (>=0.19.3) ; extra == 'training'
